{
  "season": 4,
  "board": [
    {
      "x": 0,
      "y": 0,
      "direction": 0,
      "text": "夏至",
      "note": "二十四节气之一，这一天日昼最长，夜最短"
    },
    {
      "x": 0,
      "y": 1,
      "direction": 1,
      "text": "至高无上",
      "note": "成语，指最高，没有再高了"
    },
    {
      "x": 1,
      "y": 1,
      "direction": 0,
      "text": "高丽",
      "note": "朝鲜历史上一个王朝，我国习惯上沿用此来指朝鲜"
    },
    {
      "x": 3,
      "y": 0,
      "direction": 0,
      "text": "七上八下",
      "note": "歇后语，”十五个吊桶打水”的后半句"
    },
    {
      "x": 3,
      "y": 2,
      "direction": 1,
      "text": "八仙过海",
      "note": "民间的传说故事之一，现比喻各自有一套办法，或各自施展本领，互相竞赛"
    },
    {
      "x": 6,
      "y": 0,
      "direction": 0,
      "text": "天涯海角",
      "note": "成语，形容极远的地方，或相隔极远，也是海南省三亚市著名风暴区"
    },
    {
      "x": 6,
      "y": 0,
      "direction": 1,
      "text": "天罗地网",
      "note": "成语，比喻对敌人、逃犯等的严密包围"
    },
    {
      "x": 9,
      "y": 0,
      "direction": 0,
      "text": "网开一面",
      "note": "把捕禽的网撤去三面，只留一面，比喻采取宽大态度，给人一条出路"
    },
    {
      "x": 8,
      "y": 3,
      "direction": 1,
      "text": "谜面",
      "note": "灯谜的题目，与“谜底”相对"
    },
    {
      "x": 8,
      "y": 3,
      "direction": 0,
      "text": "谜语",
      "note": "一种民间游戏，根据字面说出答案的隐语"
    },
    {
      "x": 7,
      "y": 4,
      "direction": 1,
      "text": "外语",
      "note": "外国语言"
    },
    {
      "x": 7,
      "y": 4,
      "direction": 0,
      "text": "外交官",
      "note": "代表一个国家与另一个国家办理事务的官员"
    },
    {
      "x": 5,
      "y": 6,
      "direction": 1,
      "text": "父母官",
      "note": "旧时百姓对州县官的一个称呼"
    },
    {
      "x": 6,
      "y": 6,
      "direction": 0,
      "text": "母老虎",
      "note": "雌性老虎，也比喻指凶悍的妇人"
    },
    {
      "x": 5,
      "y": 8,
      "direction": 1,
      "text": "养虎遗患",
      "note": "成语，养着老虎，留下祸患，比喻纵容坏人，给自己留下后患"
    },
    {
      "x": 8,
      "y": 8,
      "direction": 0,
      "text": "患者",
      "note": "等候接受医师的治疗与照料的病人"
    },
    {
      "x": 0,
      "y": 4,
      "direction": 1,
      "text": "自转",
      "note": "天文学名词，天体或天体系统绕质心的定点旋转"
    },
    {
      "x": 1,
      "y": 4,
      "direction": 0,
      "text": "转败为胜",
      "note": "成语，变失败为胜利"
    },
    {
      "x": 1,
      "y": 5,
      "direction": 1,
      "text": "败絮其中",
      "note": "成语“金玉其外”的下一句"
    },
    {
      "x": 0,
      "y": 7,
      "direction": 0,
      "text": "聊天室",
      "note": "人们可以在线进行实时交谈的网络交流工具"
    },
    {
      "x": 0,
      "y": 7,
      "direction": 1,
      "text": "聊胜于无",
      "note": "成语，比没有要好一点"
    },
    {
      "x": 3,
      "y": 7,
      "direction": 0,
      "text": "无机酸",
      "note": "无机化合物中酸类的总称"
    },
    {
      "x": 2,
      "y": 9,
      "direction": 1,
      "text": "碳酸饮料",
      "note": "汽水、可乐等有汽饮料的统称"
    },
    {
      "x": 5,
      "y": 8,
      "direction": 0,
      "text": "养料",
      "note": "能供给有机体营养的物质，营养品"
    }
  ]
}